Metadata-Version: 1.0
Name: mlb-distributions
Version: 0.1
Summary: Gaussian distributions
Home-page: UNKNOWN
Author: Montse Llos
Author-email: montse.llos@gmail.com
License: UNKNOWN
Platform: UNKNOWN
